LICENSE
docs/assets/logo.png
setupr/Worldr-MST-installation-PGP-key.asc
setupr/__init__.py
setupr/commands.py
setupr/console.py
setupr/downloader.py
setupr/gbucket.py
setupr/gpg.py
setupr/pre_flight.py
setupr/print.py
setupr/utils.py
setupr-0.5.2.dist-info/METADATA
setupr-0.5.2.dist-info/entry_points.txt
setupr-0.5.2.dist-info/WHEEL
setupr-0.5.2.dist-info/LICENSE
setupr-0.5.2.dist-info/RECORD
