Metadata-Version: 2.1
Name: setupr
Version: 0.5.2
Summary: Setupr ships the Worldr infrastructure.
Home-page: https://github.com/worldr/setupr
License: MIT
Keywords: worldr
Author: Dr Yann Golanski
Author-email: ygg@worldr.com
Requires-Python: >=3.8,<3.12
Classifier: License :: OSI Approved :: MIT License
Classifier: Programming Language :: Python :: 3
Classifier: Programming Language :: Python :: 3.8
Classifier: Programming Language :: Python :: 3.9
Classifier: Programming Language :: Python :: 3.10
Classifier: Programming Language :: Python :: 3.11
Requires-Dist: click (>=8.1.3,<9.0.0)
Requires-Dist: click-help-colors (>=0.9.1,<0.10.0)
Requires-Dist: distro (>=1.8.0,<2.0.0)
Requires-Dist: google-cloud-storage (>=2.5.0,<3.0.0)
Requires-Dist: pendulum (>=2.1.2,<3.0.0)
Requires-Dist: plumbum (>=1.7.2,<2.0.0)
Requires-Dist: protobuf (>=4.21.6,<5.0.0)
Requires-Dist: python-gnupg (>=0.5.0,<0.6.0)
Requires-Dist: requests (>=2.28.1,<3.0.0)
Requires-Dist: rich (>=12.4.4,<14.0.0)
Requires-Dist: ruamel.yaml (>=0.17.21,<0.18.0)
Requires-Dist: semver (>=2.10,<3)
Requires-Dist: sha256sum (>=2022.6.11,<2023.0.0)
Requires-Dist: structlog (>=22.1.0,<23.0.0)
Project-URL: Repository, https://github.com/worldr/setupr
